Workbook

Sheet Problems
A1: Status | B1: Category | C1: Subtopic | D1: Problem # | E1: Contest ID | F1: Problem Index | G1: Problem Name | H1: Rating | I1: Difficulty | J1: Topics | K1: Estimated Time (mins) | L1: XP | M1: Open Link | N1: Notes
A2: Unsolved | B2: KINGDOM 1 — THE KINGDOM OF ARRAYS | C2: Pattern 1.1 — Basic Array Traversal | D2: 263A | E2: 263 | F2: A | G2: Beautiful Matrix | H2: 800 | I2: Easy | J2: implementation | K2: 15 | L2: 10 | M2: https://codeforces.com/problemset/problem/263/A
A3: Unsolved | B3: KINGDOM 1 — THE KINGDOM OF ARRAYS | C3: Pattern 1.1 — Basic Array Traversal | D3: 266A | E3: 266 | F3: A | G3: Stones on the Table | H3: 800 | I3: Easy | J3: implementation | K3: 15 | L3: 10 | M3: https://codeforces.com/problemset/problem/266/A
A4: Unsolved | B4: KINGDOM 1 — THE KINGDOM OF ARRAYS | C4: Pattern 1.1 — Basic Array Traversal | D4: 339A | E4: 339 | F4: A | G4: Helpful Maths | H4: 800 | I4: Easy | J4: greedy, implementation, sortings, strings | K4: 15 | L4: 10 | M4: https://codeforces.com/problemset/problem/339/A
A5: Unsolved | B5: KINGDOM 1 — THE KINGDOM OF ARRAYS | C5: Pattern 1.1 — Basic Array Traversal | D5: 405A | E5: 405 | F5: A | G5: Gravity Flip | H5: 900 | I5: Easy | J5: greedy, implementation, sortings | K5: 15 | L5: 10 | M5: https://codeforces.com/problemset/problem/405/A
A6: Unsolved | B6: KINGDOM 1 — THE KINGDOM OF ARRAYS | C6: Pattern 1.1 — Basic Array Traversal | D6: 467A | E6: 467 | F6: A | G6: George and Accommodation | H6: 800 | I6: Easy | J6: implementation | K6: 15 | L6: 10 | M6: https://codeforces.com/problemset/problem/467/A
A7: Unsolved | B7: KINGDOM 1 — THE KINGDOM OF ARRAYS | C7: Pattern 1.1 — Basic Array Traversal | D7: 469A | E7: 469 | F7: A | G7: I Wanna Be the Guy | H7: 800 | I7: Easy | J7: greedy, implementation | K7: 15 | L7: 10 | M7: https://codeforces.com/problemset/problem/469/A
A8: Unsolved | B8: KINGDOM 1 — THE KINGDOM OF ARRAYS | C8: Pattern 1.1 — Basic Array Traversal | D8: 479A | E8: 479 | F8: A | G8: Expression | H8: 1000 | I8: Easy+ | J8: brute force, math | K8: 15 | L8: 10 | M8: https://codeforces.com/problemset/problem/479/A
A9: Unsolved | B9: KINGDOM 1 — THE KINGDOM OF ARRAYS | C9: Pattern 1.1 — Basic Array Traversal | D9: 490A | E9: 490 | F9: A | G9: Team Olympiad | H9: 800 | I9: Easy | J9: greedy, implementation, sortings | K9: 15 | L9: 10 | M9: https://codeforces.com/problemset/problem/490/A
A10: Unsolved | B10: KINGDOM 1 — THE KINGDOM OF ARRAYS | C10: Pattern 1.1 — Basic Array Traversal | D10: 501A | E10: 501 | F10: A | G10: Contest | H10: 900 | I10: Easy | J10: implementation | K10: 15 | L10: 10 | M10: https://codeforces.com/problemset/problem/501/A
A11: Unsolved | B11: KINGDOM 1 — THE KINGDOM OF ARRAYS | C11: Pattern 1.1 — Basic Array Traversal | D11: 509A | E11: 509 | F11: A | G11: Maximum in Table | H11: 800 | I11: Easy | J11: brute force, implementation | K11: 15 | L11: 10 | M11: https://codeforces.com/problemset/problem/509/A
A12: Unsolved | B12: KINGDOM 1 — THE KINGDOM OF ARRAYS | C12: Pattern 1.1 — Basic Array Traversal | D12: 510A | E12: 510 | F12: A | G12: Fox And Snake | H12: 800 | I12: Easy | J12: implementation | K12: 15 | L12: 10 | M12: https://codeforces.com/problemset/problem/510/A
A13: Unsolved | B13: KINGDOM 1 — THE KINGDOM OF ARRAYS | C13: Pattern 1.1 — Basic Array Traversal | D13: 581A | E13: 581 | F13: A | G13: Vasya the Hipster | H13: 800 | I13: Easy | J13: implementation, math | K13: 15 | L13: 10 | M13: https://codeforces.com/problemset/problem/581/A
... A127: Unsolved | B127: KINGDOM 1 — THE KINGDOM OF ARRAYS | C127: Pattern 1.5 — Coordinate Compression | D127: 1208B | E127: 1208 | F127: B | G127: Uniqueness | H127: 1500 | I127: Medium+ | J127: binary search, brute force, implementation, two pointers | K127: 40 | L127: 35 | M127: https://codeforces.com/problemset/problem/1208/B
A128: Unsolved | B128: KINGDOM 1 — THE KINGDOM OF ARRAYS | C128: Pattern 1.5 — Coordinate Compression | D128: 1230C | E128: 1230 | F128: C | G128: UNKNOWN | H128: UNKNOWN | I128: UNKNOWN | J128: UNKNOWN | K128: 0 | L128: 0 | M128: https://codeforces.com/problemset/problem/1230/C
A129: Unsolved | B129: KINGDOM 1 — THE KINGDOM OF ARRAYS | C129: Pattern 1.5 — Coordinate Compression | D129: 1324D | E129: 1324 | F129: D | G129: Pair of Topics | H129: 1400 | I129: Medium | J129: binary search, data structures, sortings, two pointers | K129: 40 | L129: 35 | M129: https://codeforces.com/problemset/problem/1324/D
A130: Unsolved | B130: KINGDOM 1 — THE KINGDOM OF ARRAYS | C130: Pattern 1.5 — Coordinate Compression | D130: 1355C | E130: 1355 | F130: C | G130: Count Triangles | H130: 1800 | I130: Hard | J130: binary search, implementation, math, two pointers | K130: 60 | L130: 55 | M130: https://codeforces.com/problemset/problem/1355/C
A131: Unsolved | B131: KINGDOM 1 — THE KINGDOM OF ARRAYS | C131: Pattern 1.5 — Coordinate Compression | D131: 1400C | E131: 1400 | F131: C | G131: Binary String Reconstruction | H131: 1500 | I131: Medium+ | J131: 2-sat, brute force, constructive algorithms, greedy | K131: 40 | L131: 35 | M131: https://codeforces.com/problemset/problem/1400/C
A132: Unsolved | B132: KINGDOM 1 — THE KINGDOM OF ARRAYS | C132: Pattern 1.5 — Coordinate Compression | D132: 1473D | E132: 1473 | F132: D | G132: Program | H132: 1700 | I132: Hard | J132: data structures, dp, implementation, strings | K132: 60 | L132: 55 | M132: https://codeforces.com/problemset/problem/1473/D
A133: Unsolved | B133: KINGDOM 1 — THE KINGDOM OF ARRAYS | C133: Pattern 1.5 — Coordinate Compression | D133: 1490D | E133: 1490 | F133: D | G133: Permutation Transformation | H133: 1200 | I133: Easy+ | J133: dfs and similar, divide and conquer, implementation | K133: 25 | L133: 20 | M133: https://codeforces.com/problemset/problem/1490/D
A134: Unsolved | B134: KINGDOM 1 — THE KINGDOM OF ARRAYS | C134: Pattern 1.5 — Coordinate Compression | D134: 1512D | E134: 1512 | F134: D | G134: Corrupted Array | H134: 1200 | I134: Easy+ | J134: constructive algorithms, data structures, greedy | K134: 25 | L134: 20 | M134: https://codeforces.com/problemset/problem/1512/D
A135: Unsolved | B135: KINGDOM 1 — THE KINGDOM OF ARRAYS | C135: Pattern 1.5 — Coordinate Compression | D135: 1547C | E135: 1547 | F135: C | G135: Pair Programming | H135: 1100 | I135: Easy+ | J135: greedy, two pointers | K135: 25 | L135: 20 | M135: https://codeforces.com/problemset/problem/1547/C
A136: Unsolved | B136: KINGDOM 1 — THE KINGDOM OF ARRAYS | C136: Pattern 1.5 — Coordinate Compression | D136: 1567C | E136: 1567 | F136: C | G136: Carrying Conundrum | H136: 1600 | I136: Medium+ | J136: bitmasks, combinatorics, dp, math | K136: 40 | L136: 35 | M136: https://codeforces.com/problemset/problem/1567/C
A137: Unsolved | B137: KINGDOM 1 — THE KINGDOM OF ARRAYS | C137: Pattern 1.6 — Constructive Arrays | D137: 1251C | E137: 1251 | F137: C | G137: Minimize The Integer | H137: 1600 | I137: Medium+ | J137: greedy, two pointers | K137: 40 | L137: 35 | M137: https://codeforces.com/problemset/problem/1251/C
A138: Unsolved | B138: KINGDOM 1 — THE KINGDOM OF ARRAYS | C138: Pattern 1.6 — Constructive Arrays | D138: 1288D | E138: 1288 | F138: D | G138: Minimax Problem | H138: 2000 | I138: Hard+ | J138: binary search, bitmasks, dp | K138: 90 | L138: 80 | M138: https://codeforces.com/problemset/problem/1288/D
A139: Unsolved | B139: KINGDOM 1 — THE KINGDOM OF ARRAYS | C139: Pattern 1.6 — Constructive Arrays | D139: 1370D | E139: 1370 | F139: D | G139: Odd-Even Subsequence | H139: 2000 | I139: Hard+ | J139: binary search, dp, dsu, greedy, implementation | K139: 90 | L139: 80 | M139: https://codeforces.com/problemset/problem/1370/D
A140: Unsolved | B140: KINGDOM 1 — THE KINGDOM OF ARRAYS | C140: Pattern 1.6 — Constructive Arrays | D140: 1407D | E140: 1407 | F140: D | G140: Discrete Centrifugal Jumps | H140: 2200 | I140: Expert | J140: data structures, dp, graphs | K140: 90 | L140: 80 | M140: https://codeforces.com/problemset/problem/1407/D
... A152: Unsolved | B152: KINGDOM 2 — THE KINGDOM OF PREFIX SUM & DIFFERENCE ARRAY | C152: Pattern 2.1 — 1D Prefix Sum | D152: 816B | E152: 816 | F152: B | G152: Karen and Coffee | H152: 1400 | I152: Medium | J152: binary search, data structures, implementation | K152: 40 | L152: 35 | M152: https://codeforces.com/problemset/problem/816/B
A153: Unsolved | B153: KINGDOM 2 — THE KINGDOM OF PREFIX SUM & DIFFERENCE ARRAY | C153: Pattern 2.1 — 1D Prefix Sum | D153: 1191C | E153: 1191 | F153: C | G153: UNKNOWN | H153: UNKNOWN | I153: UNKNOWN | J153: UNKNOWN | K153: 0 | L153: 0 | M153: https://codeforces.com/problemset/problem/1191/C
A154: Unsolved | B154: KINGDOM 2 — THE KINGDOM OF PREFIX SUM & DIFFERENCE ARRAY | C154: Pattern 2.1 — 1D Prefix Sum | D154: 1272C | E154: 1272 | F154: C | G154: Yet Another Broken Keyboard | H154: 1200 | I154: Easy+ | J154: combinatorics, dp, implementation | K154: 25 | L154: 20 | M154: https://codeforces.com/problemset/problem/1272/C
A155: Unsolved | B155: KINGDOM 2 — THE KINGDOM OF PREFIX SUM & DIFFERENCE ARRAY | C155: Pattern 2.1 — 1D Prefix Sum | D155: 1363A | E155: 1363 | F155: A | G155: Odd Selection | H155: 1200 | I155: Easy+ | J155: brute force, implementation, math | K155: 25 | L155: 20 | M155: https://codeforces.com/problemset/problem/1363/A
A156: Unsolved | B156: KINGDOM 2 — THE KINGDOM OF PREFIX SUM & DIFFERENCE ARRAY | C156: Pattern 2.1 — 1D Prefix Sum | D156: 1392D | E156: 1392 | F156: D | G156: Omkar and Bed Wars | H156: 1700 | I156: Hard | J156: dp, greedy | K156: 60 | L156: 55 | M156: https://codeforces.com/problemset/problem/1392/D
A157: Unsolved | B157: KINGDOM 2 — THE KINGDOM OF PREFIX SUM & DIFFERENCE ARRAY | C157: Pattern 2.1 — 1D Prefix Sum | D157: 1430D | E157: 1430 | F157: D | G157: String Deletion | H157: 1700 | I157: Hard | J157: binary search, data structures, greedy, two pointers | K157: 60 | L157: 55 | M157: https://codeforces.com/problemset/problem/1430/D
A158: Unsolved | B158: KINGDOM 2 — THE KINGDOM OF PREFIX SUM & DIFFERENCE ARRAY | C158: Pattern 2.2 — Prefix Frequency | D158: 1114C | E158: 1114 | F158: C | G158: Trailing Loves (or L'oeufs?) | H158: 1700 | I158: Hard | J158: brute force, implementation, math, number theory | K158: 60 | L158: 55 | M158: https://codeforces.com/problemset/problem/1114/C
A159: Unsolved | B159: KINGDOM 2 — THE KINGDOM OF PREFIX SUM & DIFFERENCE ARRAY | C159: Pattern 2.2 — Prefix Frequency | D159: 1141D | E159: 1141 | F159: D | G159: Colored Boots | H159: 1500 | I159: Medium+ | J159: greedy, implementation | K159: 40 | L159: 35 | M159: https://codeforces.com/problemset/problem/1141/D
A160: Unsolved | B160: KINGDOM 2 — THE KINGDOM OF PREFIX SUM & DIFFERENCE ARRAY | C160: Pattern 2.2 — Prefix Frequency | D160: 1238E | E160: 1238 | F160: E | G160: Keyboard Purchase | H160: 2200 | I160: Expert | J160: bitmasks, dp | K160: 90 | L160: 80 | M160: https://codeforces.com/problemset/problem/1238/E
A161: Unsolved | B161: KINGDOM 2 — THE KINGDOM OF PREFIX SUM & DIFFERENCE ARRAY | C161: Pattern 2.2 — Prefix Frequency | D161: 1285B | E161: 1285 | F161: B | G161: Just Eat It! | H161: 1300 | I161: Medium | J161: dp, greedy, implementation | K161: 25 | L161: 20 | M161: https://codeforces.com/problemset/problem/1285/B
A162: Unsolved | B162: KINGDOM 2 — THE KINGDOM OF PREFIX SUM & DIFFERENCE ARRAY | C162: Pattern 2.2 — Prefix Frequency | D162: 1303C | E162: 1303 | F162: C | G162: Perfect Keyboard | H162: 1600 | I162: Medium+ | J162: dfs and similar, greedy, implementation | K162: 40 | L162: 35 | M162: https://codeforces.com/problemset/problem/1303/C
A163: Unsolved | B163: KINGDOM 2 — THE KINGDOM OF PREFIX SUM & DIFFERENCE ARRAY | C163: Pattern 2.2 — Prefix Frequency | D163: 1437C | E163: 1437 | F163: C | G163: Chef Monocarp | H163: 1800 | I163: Hard | J163: dp, flows, graph matchings, greedy, math, sortings | K163: 60 | L163: 55 | M163: https://codeforces.com/problemset/problem/1437/C
A164: Unsolved | B164: KINGDOM 2 — THE KINGDOM OF PREFIX SUM & DIFFERENCE ARRAY | C164: Pattern 2.2 — Prefix Frequency | D164: 1498C | E164: 1498 | F164: C | G164: Planar Reflections | H164: 1600 | I164: Medium+ | J164: brute force, data structures, dp | K164: 40 | L164: 35 | M164: https://codeforces.com/problemset/problem/1498/C
A165: Unsolved | B165: KINGDOM 2 — THE KINGDOM OF PREFIX SUM & DIFFERENCE ARRAY | C165: Pattern 2.2 — Prefix Frequency | D165: 1513C | E165: 1513 | F165: C | G165: Add One | H165: 1600 | I165: Medium+ | J165: dp, matrices | K165: 40 | L165: 35 | M165: https://codeforces.com/problemset/problem/1513/C
... A209: Unsolved | B209: KINGDOM 3 — THE KINGDOM OF TWO POINTERS & SLIDING WINDOW | C209: Pattern 3.3 — Sliding Window | D209: 1539C | E209: 1539 | F209: C | G209: Stable Groups | H209: 1200 | I209: Easy+ | J209: greedy, sortings | K209: 25 | L209: 20 | M209: https://codeforces.com/problemset/problem/1539/C
A210: Unsolved | B210: KINGDOM 3 — THE KINGDOM OF TWO POINTERS & SLIDING WINDOW | C210: Pattern 3.3 — Sliding Window | D210: 1561B | E210: 1561 | F210: B | G210: UNKNOWN | H210: UNKNOWN | I210: UNKNOWN | J210: UNKNOWN | K210: 0 | L210: 0 | M210: https://codeforces.com/problemset/problem/1561/B
A211: Unsolved | B211: KINGDOM 3 — THE KINGDOM OF TWO POINTERS & SLIDING WINDOW | C211: Pattern 3.4 — Meet in the Middle Style | D211: 525E | E211: 525 | F211: E | G211: Anya and Cubes | H211: 2100 | I211: Expert | J211: binary search, bitmasks, brute force, dp, math, meet-in-the-middle | K211: 90 | L211: 80 | M211: https://codeforces.com/problemset/problem/525/E
A212: Unsolved | B212: KINGDOM 3 — THE KINGDOM OF TWO POINTERS & SLIDING WINDOW | C212: Pattern 3.4 — Meet in the Middle Style | D212: 888E | E212: 888 | F212: E | G212: Maximum Subsequence | H212: 1800 | I212: Hard | J212: bitmasks, divide and conquer, meet-in-the-middle | K212: 60 | L212: 55 | M212: https://codeforces.com/problemset/problem/888/E
A213: Unsolved | B213: KINGDOM 3 — THE KINGDOM OF TWO POINTERS & SLIDING WINDOW | C213: Pattern 3.4 — Meet in the Middle Style | D213: 1006F | E213: 1006 | F213: F | G213: Xor-Paths | H213: 2100 | I213: Expert | J213: bitmasks, brute force, dp, meet-in-the-middle | K213: 90 | L213: 80 | M213: https://codeforces.com/problemset/problem/1006/F
A214: Unsolved | B214: KINGDOM 3 — THE KINGDOM OF TWO POINTERS & SLIDING WINDOW | C214: Pattern 3.4 — Meet in the Middle Style | D214: 1197D | E214: 1197 | F214: D | G214: Yet Another Subarray Problem | H214: 1900 | I214: Hard+ | J214: dp, greedy, math | K214: 60 | L214: 55 | M214: https://codeforces.com/problemset/problem/1197/D
A215: Unsolved | B215: KINGDOM 3 — THE KINGDOM OF TWO POINTERS & SLIDING WINDOW | C215: Pattern 3.4 — Meet in the Middle Style | D215: 1239A | E215: 1239 | F215: A | G215: Ivan the Fool and the Probability Theory | H215: 1700 | I215: Hard | J215: combinatorics, dp, math | K215: 60 | L215: 55 | M215: https://codeforces.com/problemset/problem/1239/A
A216: Unsolved | B216: KINGDOM 3 — THE KINGDOM OF TWO POINTERS & SLIDING WINDOW | C216: Pattern 3.4 — Meet in the Middle Style | D216: 1325E | E216: 1325 | F216: E | G216: Ehab's REAL Number Theory Problem | H216: 2600 | I216: Master | J216: brute force, dfs and similar, graphs, number theory, shortest paths | K216: 180 | L216: 150 | M216: https://codeforces.com/problemset/problem/1325/E
A217: Unsolved | B217: KINGDOM 4 — THE KINGDOM OF BINARY SEARCH | C217: Pattern 4.1 — Classic Binary Search | D217: 492B | E217: 492 | F217: B | G217: Vanya and Lanterns | H217: 1200 | I217: Easy+ | J217: binary search, implementation, math, sortings | K217: 25 | L217: 20 | M217: https://codeforces.com/problemset/problem/492/B
A218: Unsolved | B218: KINGDOM 4 — THE KINGDOM OF BINARY SEARCH | C218: Pattern 4.1 — Classic Binary Search | D218: 371C | E218: 371 | F218: C | G218: Hamburgers | H218: 1600 | I218: Medium+ | J218: binary search, brute force | K218: 40 | L218: 35 | M218: https://codeforces.com/problemset/problem/371/C
A219: Unsolved | B219: KINGDOM 4 — THE KINGDOM OF BINARY SEARCH | C219: Pattern 4.1 — Classic Binary Search | D219: 1251D | E219: 1251 | F219: D | G219: Salary Changing | H219: 1900 | I219: Hard+ | J219: binary search, greedy, sortings | K219: 60 | L219: 55 | M219: https://codeforces.com/problemset/problem/1251/D
A220: Unsolved | B220: KINGDOM 4 — THE KINGDOM OF BINARY SEARCH | C220: Pattern 4.1 — Classic Binary Search | D220: 1468D | E220: 1468 | F220: D | G220: Firecrackers | H220: 1700 | I220: Hard | J220: binary search, sortings | K220: 60 | L220: 55 | M220: https://codeforces.com/problemset/problem/1468/D
A221: Unsolved | B221: KINGDOM 4 — THE KINGDOM OF BINARY SEARCH | C221: Pattern 4.2 — Binary Search on Answer | D221: 670D2 | E221: 670 | F221: D2 | G221: Magic Powder - 2 | H221: 1500 | I221: Medium+ | J221: binary search, implementation | K221: 40 | L221: 35 | M221: https://codeforces.com/problemset/problem/670/D2
A222: Unsolved | B222: KINGDOM 4 — THE KINGDOM OF BINARY SEARCH | C222: Pattern 4.2 — Binary Search on Answer | D222: 1117C | E222: 1117 | F222: C | G222: Magic Ship | H222: 1900 | I222: Hard+ | J222: binary search | K222: 60 | L222: 55 | M222: https://codeforces.com/problemset/problem/1117/C
... A302: Unsolved | B302: KINGDOM 6 — THE KINGDOM OF STRINGS | C302: Pattern 6.3 — Greedy on Strings | D302: 1367D | E302: 1367 | F302: D | G302: Task On The Board | H302: 1800 | I302: Hard | J302: constructive algorithms, greedy, implementation, sortings | K302: 60 | L302: 55 | M302: https://codeforces.com/problemset/problem/1367/D
A303: Unsolved | B303: KINGDOM 6 — THE KINGDOM OF STRINGS | C303: Pattern 6.3 — Greedy on Strings | D303: 1382C1 | E303: 1382 | F303: C1 | G303: UNKNOWN | H303: UNKNOWN | I303: UNKNOWN | J303: UNKNOWN | K303: 0 | L303: 0 | M303: https://codeforces.com/problemset/problem/1382/C1
A304: Unsolved | B304: KINGDOM 6 — THE KINGDOM OF STRINGS | C304: Pattern 6.3 — Greedy on Strings | D304: 1382C2 | E304: 1382 | F304: C2 | G304: UNKNOWN | H304: UNKNOWN | I304: UNKNOWN | J304: UNKNOWN | K304: 0 | L304: 0 | M304: https://codeforces.com/problemset/problem/1382/C2
A305: Unsolved | B305: KINGDOM 6 — THE KINGDOM OF STRINGS | C305: Pattern 6.3 — Greedy on Strings | D305: 1430E | E305: 1430 | F305: E | G305: String Reversal | H305: 1900 | I305: Hard+ | J305: data structures, greedy, strings | K305: 60 | L305: 55 | M305: https://codeforces.com/problemset/problem/1430/E
A306: Unsolved | B306: KINGDOM 6 — THE KINGDOM OF STRINGS | C306: Pattern 6.3 — Greedy on Strings | D306: 1451C | E306: 1451 | F306: C | G306: String Equality | H306: 1400 | I306: Medium | J306: dp, greedy, hashing, implementation, strings | K306: 40 | L306: 35 | M306: https://codeforces.com/problemset/problem/1451/C
A307: Unsolved | B307: KINGDOM 6 — THE KINGDOM OF STRINGS | C307: Pattern 6.3 — Greedy on Strings | D307: 1493C | E307: 1493 | F307: C | G307: K-beautiful Strings | H307: 2000 | I307: Hard+ | J307: binary search, brute force, constructive algorithms, greedy, strings | K307: 90 | L307: 80 | M307: https://codeforces.com/problemset/problem/1493/C
A308: Unsolved | B308: KINGDOM 6 — THE KINGDOM OF STRINGS | C308: Pattern 6.4 — Prefix Function (KMP) | D308: 126B | E308: 126 | F308: B | G308: Password | H308: 1700 | I308: Hard | J308: binary search, dp, hashing, string suffix structures, strings | K308: 60 | L308: 55 | M308: https://codeforces.com/problemset/problem/126/B
A309: Unsolved | B309: KINGDOM 6 — THE KINGDOM OF STRINGS | C309: Pattern 6.4 — Prefix Function (KMP) | D309: 432D | E309: 432 | F309: D | G309: Prefixes and Suffixes | H309: 2000 | I309: Hard+ | J309: dp, string suffix structures, strings, two pointers | K309: 90 | L309: 80 | M309: https://codeforces.com/problemset/problem/432/D
A310: Unsolved | B310: KINGDOM 6 — THE KINGDOM OF STRINGS | C310: Pattern 6.4 — Prefix Function (KMP) | D310: 471D | E310: 471 | F310: D | G310: MUH and Cube Walls | H310: 1800 | I310: Hard | J310: string suffix structures, strings | K310: 60 | L310: 55 | M310: https://codeforces.com/problemset/problem/471/D
A311: Unsolved | B311: KINGDOM 6 — THE KINGDOM OF STRINGS | C311: Pattern 6.4 — Prefix Function (KMP) | D311: 526D | E311: 526 | F311: D | G311: Om Nom and Necklace | H311: 2200 | I311: Expert | J311: hashing, string suffix structures, strings | K311: 90 | L311: 80 | M311: https://codeforces.com/problemset/problem/526/D
A312: Unsolved | B312: KINGDOM 6 — THE KINGDOM OF STRINGS | C312: Pattern 6.4 — Prefix Function (KMP) | D312: 808G | E312: 808 | F312: G | G312: Anthem of Berland | H312: 2300 | I312: Expert | J312: dp, strings | K312: 120 | L312: 110 | M312: https://codeforces.com/problemset/problem/808/G
A313: Unsolved | B313: KINGDOM 6 — THE KINGDOM OF STRINGS | C313: Pattern 6.4 — Prefix Function (KMP) | D313: 1326D2 | E313: 1326 | F313: D2 | G313: Prefix-Suffix Palindrome (Hard version) | H313: 1800 | I313: Hard | J313: binary search, greedy, hashing, string suffix structures, strings | K313: 60 | L313: 55 | M313: https://codeforces.com/problemset/problem/1326/D2
A314: Unsolved | B314: KINGDOM 6 — THE KINGDOM OF STRINGS | C314: Pattern 6.4 — Prefix Function (KMP) | D314: 1721E | E314: 1721 | F314: E | G314: Prefix Function Queries | H314: 2200 | I314: Expert | J314: dfs and similar, dp, hashing, string suffix structures, strings, trees | K314: 90 | L314: 80 | M314: https://codeforces.com/problemset/problem/1721/E
A315: Unsolved | B315: KINGDOM 6 — THE KINGDOM OF STRINGS | C315: Pattern 6.5 — Z Algorithm | D315: 196B | E315: 196 | F315: B | G315: Infinite Maze | H315: 2000 | I315: Hard+ | J315: dfs and similar, graphs | K315: 90 | L315: 80 | M315: https://codeforces.com/problemset/problem/196/B
A316: Unsolved | B316: KINGDOM 6 — THE KINGDOM OF STRINGS | C316: Pattern 6.5 — Z Algorithm | D316: 535D | E316: 535 | F316: D | G316: Tavas and Malekas | H316: 1900 | I316: Hard+ | J316: greedy, hashing, string suffix structures, strings | K316: 60 | L316: 55 | M316: https://codeforces.com/problemset/problem/535/D
... A333: Unsolved | B333: KINGDOM 7 — THE KINGDOM OF BIT MANIPULATION | C333: Pattern 7.1 — Basic Bit Operations | D333: 1438A | E333: 1438 | F333: A | G333: Specific Tastes of Andre | H333: 800 | I333: Easy | J333: constructive algorithms, implementation | K333: 15 | L333: 10 | M333: https://codeforces.com/problemset/problem/1438/A
A334: Unsolved | B334: KINGDOM 7 — THE KINGDOM OF BIT MANIPULATION | C334: Pattern 7.1 — Basic Bit Operations | D334: 1457A | E334: 1457 | F334: A | G334: UNKNOWN | H334: UNKNOWN | I334: UNKNOWN | J334: UNKNOWN | K334: 0 | L334: 0 | M334: https://codeforces.com/problemset/problem/1457/A
A335: Unsolved | B335: KINGDOM 7 — THE KINGDOM OF BIT MANIPULATION | C335: Pattern 7.1 — Basic Bit Operations | D335: 1491A | E335: 1491 | F335: A | G335: K-th Largest Value | H335: 800 | I335: Easy | J335: brute force, greedy, implementation | K335: 15 | L335: 10 | M335: https://codeforces.com/problemset/problem/1491/A
A336: Unsolved | B336: KINGDOM 7 — THE KINGDOM OF BIT MANIPULATION | C336: Pattern 7.1 — Basic Bit Operations | D336: 1501A | E336: 1501 | F336: A | G336: Alexey and Train | H336: 800 | I336: Easy | J336: implementation | K336: 15 | L336: 10 | M336: https://codeforces.com/problemset/problem/1501/A
A337: Unsolved | B337: KINGDOM 7 — THE KINGDOM OF BIT MANIPULATION | C337: Pattern 7.1 — Basic Bit Operations | D337: 1525A | E337: 1525 | F337: A | G337: Potion-making | H337: 800 | I337: Easy | J337: math, number theory | K337: 15 | L337: 10 | M337: https://codeforces.com/problemset/problem/1525/A
A338: Unsolved | B338: KINGDOM 7 — THE KINGDOM OF BIT MANIPULATION | C338: Pattern 7.2 — XOR Properties | D338: 276D | E338: 276 | F338: D | G338: Little Girl and Maximum XOR | H338: 1700 | I338: Hard | J338: bitmasks, dp, greedy, implementation, math | K338: 60 | L338: 55 | M338: https://codeforces.com/problemset/problem/276/D
A339: Unsolved | B339: KINGDOM 7 — THE KINGDOM OF BIT MANIPULATION | C339: Pattern 7.2 — XOR Properties | D339: 282E | E339: 282 | F339: E | G339: Sausage Maximization | H339: 2200 | I339: Expert | J339: bitmasks, data structures, trees | K339: 90 | L339: 80 | M339: https://codeforces.com/problemset/problem/282/E
A340: Unsolved | B340: KINGDOM 7 — THE KINGDOM OF BIT MANIPULATION | C340: Pattern 7.2 — XOR Properties | D340: 429A | E340: 429 | F340: A | G340: Xor-tree | H340: 1300 | I340: Medium | J340: dfs and similar, trees | K340: 25 | L340: 20 | M340: https://codeforces.com/problemset/problem/429/A
A341: Unsolved | B341: KINGDOM 7 — THE KINGDOM OF BIT MANIPULATION | C341: Pattern 7.3 — Bitmask Enumeration | D341: 319B | E341: 319 | F341: B | G341: Psychos in a Line | H341: 1900 | I341: Hard+ | J341: data structures, implementation | K341: 60 | L341: 55 | M341: https://codeforces.com/problemset/problem/319/B
A342: Unsolved | B342: KINGDOM 7 — THE KINGDOM OF BIT MANIPULATION | C342: Pattern 7.3 — Bitmask Enumeration | D342: 580D | E342: 580 | F342: D | G342: Kefa and Dishes | H342: 1800 | I342: Hard | J342: bitmasks, dp | K342: 60 | L342: 55 | M342: https://codeforces.com/problemset/problem/580/D
A343: Unsolved | B343: KINGDOM 7 — THE KINGDOM OF BIT MANIPULATION | C343: Pattern 7.3 — Bitmask Enumeration | D343: 839C | E343: 839 | F343: C | G343: Journey | H343: 1500 | I343: Medium+ | J343: dfs and similar, dp, graphs, probabilities, trees | K343: 40 | L343: 35 | M343: https://codeforces.com/problemset/problem/839/C
A344: Unsolved | B344: KINGDOM 7 — THE KINGDOM OF BIT MANIPULATION | C344: Pattern 7.3 — Bitmask Enumeration | D344: 1102F | E344: 1102 | F344: F | G344: Elongated Matrix | H344: 2000 | I344: Hard+ | J344: binary search, bitmasks, brute force, dp, graphs | K344: 90 | L344: 80 | M344: https://codeforces.com/problemset/problem/1102/F
A345: Unsolved | B345: KINGDOM 7 — THE KINGDOM OF BIT MANIPULATION | C345: Pattern 7.3 — Bitmask Enumeration | D345: 1316E | E345: 1316 | F345: E | G345: Team Building | H345: 2300 | I345: Expert | J345: bitmasks, dp, greedy, sortings | K345: 120 | L345: 110 | M345: https://codeforces.com/problemset/problem/1316/E
A346: Unsolved | B346: KINGDOM 7 — THE KINGDOM OF BIT MANIPULATION | C346: Pattern 7.3 — Bitmask Enumeration | D346: 1523D | E346: 1523 | F346: D | G346: Love-Hate | H346: 2400 | I346: Master | J346: bitmasks, brute force, dp, probabilities | K346: 120 | L346: 110 | M346: https://codeforces.com/problemset/problem/1523/D
... A349: Unsolved | B349: KINGDOM 7 — THE KINGDOM OF BIT MANIPULATION | C349: Pattern 7.4 — Trie + XOR | D349: 923C | E349: 923 | F349: C | G349: Perfect Security | H349: 1800 | I349: Hard | J349: data structures, greedy, strings, trees | K349: 60 | L349: 55 | M349: https://codeforces.com/problemset/problem/923/C
A350: Unsolved | B350: KINGDOM 7 — THE KINGDOM OF BIT MANIPULATION | C350: Pattern 7.4 — Trie + XOR | D350: 948D | E350: 948 | F350: D | G350: UNKNOWN | H350: UNKNOWN | I350: UNKNOWN | J350: UNKNOWN | K350: 0 | L350: 0 | M350: https://codeforces.com/problemset/problem/948/D
A351: Unsolved | B351: KINGDOM 7 — THE KINGDOM OF BIT MANIPULATION | C351: Pattern 7.4 — Trie + XOR | D351: 1285D | E351: 1285 | F351: D | G351: Dr. Evil Underscores | H351: 1900 | I351: Hard+ | J351: bitmasks, brute force, dfs and similar, divide and conquer, dp, greedy, strings, trees | K351: 60 | L351: 55 | M351: https://codeforces.com/problemset/problem/1285/D
A352: Unsolved | B352: KINGDOM 7 — THE KINGDOM OF BIT MANIPULATION | C352: Pattern 7.4 — Trie + XOR | D352: 1447E | E352: 1447 | F352: E | G352: UNKNOWN | H352: UNKNOWN | I352: UNKNOWN | J352: UNKNOWN | K352: 0 | L352: 0 | M352: https://codeforces.com/problemset/problem/1447/E
A353: Unsolved | B353: KINGDOM 7 — THE KINGDOM OF BIT MANIPULATION | C353: Pattern 7.4 — Trie + XOR | D353: 1658D2 | E353: 1658 | F353: D2 | G353: 388535 (Hard Version) | H353: 2300 | I353: Expert | J353: bitmasks, brute force, data structures, math | K353: 120 | L353: 110 | M353: https://codeforces.com/problemset/problem/1658/D2
A354: Unsolved | B354: KINGDOM 8 — THE KINGDOM OF MATHEMATICS & NUMBER THEORY | C354: Pattern 8.1 — Basic Mathematics | D354: 50A | E354: 50 | F354: A | G354: Domino piling | H354: 800 | I354: Easy | J354: greedy, math | K354: 15 | L354: 10 | M354: https://codeforces.com/problemset/problem/50/A
A355: Unsolved | B355: KINGDOM 8 — THE KINGDOM OF MATHEMATICS & NUMBER THEORY | C355: Pattern 8.1 — Basic Mathematics | D355: 617A | E355: 617 | F355: A | G355: Elephant | H355: 800 | I355: Easy | J355: math | K355: 15 | L355: 10 | M355: https://codeforces.com/problemset/problem/617/A
A356: Unsolved | B356: KINGDOM 8 — THE KINGDOM OF MATHEMATICS & NUMBER THEORY | C356: Pattern 8.1 — Basic Mathematics | D356: 630A | E356: 630 | F356: A | G356: Again Twenty Five! | H356: 800 | I356: Easy | J356: number theory | K356: 15 | L356: 10 | M356: https://codeforces.com/problemset/problem/630/A
A357: Unsolved | B357: KINGDOM 8 — THE KINGDOM OF MATHEMATICS & NUMBER THEORY | C357: Pattern 8.1 — Basic Mathematics | D357: 742A | E357: 742 | F357: A | G357: Arpa’s hard exam and Mehrdad’s naive cheat | H357: 1000 | I357: Easy+ | J357: implementation, math, number theory | K357: 15 | L357: 10 | M357: https://codeforces.com/problemset/problem/742/A
A358: Unsolved | B358: KINGDOM 8 — THE KINGDOM OF MATHEMATICS & NUMBER THEORY | C358: Pattern 8.1 — Basic Mathematics | D358: 732A | E358: 732 | F358: A | G358: Buy a Shovel | H358: 800 | I358: Easy | J358: brute force, constructive algorithms, implementation, math | K358: 15 | L358: 10 | M358: https://codeforces.com/problemset/problem/732/A
A359: Unsolved | B359: KINGDOM 8 — THE KINGDOM OF MATHEMATICS & NUMBER THEORY | C359: Pattern 8.1 — Basic Mathematics | D359: 977A | E359: 977 | F359: A | G359: Wrong Subtraction | H359: 800 | I359: Easy | J359: implementation | K359: 15 | L359: 10 | M359: https://codeforces.com/problemset/problem/977/A
A360: Unsolved | B360: KINGDOM 8 — THE KINGDOM OF MATHEMATICS & NUMBER THEORY | C360: Pattern 8.1 — Basic Mathematics | D360: 1154A | E360: 1154 | F360: A | G360: Restoring Three Numbers | H360: 800 | I360: Easy | J360: math | K360: 15 | L360: 10 | M360: https://codeforces.com/problemset/problem/1154/A
A361: Unsolved | B361: KINGDOM 8 — THE KINGDOM OF MATHEMATICS & NUMBER THEORY | C361: Pattern 8.1 — Basic Mathematics | D361: 119A | E361: 119 | F361: A | G361: Epic Game | H361: 800 | I361: Easy | J361: implementation | K361: 15 | L361: 10 | M361: https://codeforces.com/problemset/problem/119/A
A362: Unsolved | B362: KINGDOM 8 — THE KINGDOM OF MATHEMATICS & NUMBER THEORY | C362: Pattern 8.1 — Basic Mathematics | D362: 1204A | E362: 1204 | F362: A | G362: BowWow and the Timetable | H362: 1000 | I362: Easy+ | J362: math | K362: 15 | L362: 10 | M362: https://codeforces.com/problemset/problem/1204/A
A363: Unsolved | B363: KINGDOM 8 — THE KINGDOM OF MATHEMATICS & NUMBER THEORY | C363: Pattern 8.1 — Basic Mathematics | D363: 1220A | E363: 1220 | F363: A | G363: Cards | H363: 800 | I363: Easy | J363: implementation, sortings, strings | K363: 15 | L363: 10 | M363: https://codeforces.com/problemset/problem/1220/A
A364: Unsolved | B364: KINGDOM 8 — THE KINGDOM OF MATHEMATICS & NUMBER THEORY | C364: Pattern 8.1 — Basic Mathematics | D364: 1245A | E364: 1245 | F364: A | G364: Good ol' Numbers Coloring | H364: 1000 | I364: Easy+ | J364: math, number theory | K364: 15 | L364: 10 | M364: https://codeforces.com/problemset/problem/1245/A
...

Sheet Kingdom Summary
A1: Kingdom | B1: Patterns | C1: Total Problems | D1: Verified Problems | E1: Solved | F1: Completion % | G1: Total XP | H1: Average Rating
A2: KINGDOM 1 — THE KINGDOM OF ARRAYS | B2: 6 | C2: =COUNTIF(Problems!$B:$B, A2) -> 146 | D2: =COUNTIFS(Problems!$B:$B, A2, Problems!$G:$G, "<>UNKNOWN") -> 145 | E2: =COUNTIFS(Problems!$B:$B, A2, Problems!$A:$A, "Solved") -> 0 | F2: =IF(C2>0, E2/C2, 0) -> 0 | G2: =SUMIF(Problems!$B:$B, A2, Problems!$L:$L) -> 2945 | H2: =AVERAGEIF(Problems!$B:$B, A2, Problems!$H:$H) -> 1086.2069
A3: KINGDOM 2 — THE KINGDOM OF PREFIX SUM & DIFFERENCE ARRAY | B3: 4 | C3: =COUNTIF(Problems!$B:$B, A3) -> 36 | D3: =COUNTIFS(Problems!$B:$B, A3, Problems!$G:$G, "<>UNKNOWN") -> 35 | E3: =COUNTIFS(Problems!$B:$B, A3, Problems!$A:$A, "Solved") -> 0 | F3: =IF(C3>0, E3/C3, 0) -> 0 | G3: =SUMIF(Problems!$B:$B, A3, Problems!$L:$L) -> 1820 | H3: =AVERAGEIF(Problems!$B:$B, A3, Problems!$H:$H) -> 1720
A4: KINGDOM 3 — THE KINGDOM OF TWO POINTERS & SLIDING WINDOW | B4: 4 | C4: =COUNTIF(Problems!$B:$B, A4) -> 33 | D4: =COUNTIFS(Problems!$B:$B, A4, Problems!$G:$G, "<>UNKNOWN") -> 32 | E4: =COUNTIFS(Problems!$B:$B, A4, Problems!$A:$A, "Solved") -> 0 | F4: =IF(C4>0, E4/C4, 0) -> 0 | G4: =SUMIF(Problems!$B:$B, A4, Problems!$L:$L) -> 1355 | H4: =AVERAGEIF(Problems!$B:$B, A4, Problems!$H:$H) -> 1562.5
A5: KINGDOM 4 — THE KINGDOM OF BINARY SEARCH | B5: 4 | C5: =COUNTIF(Problems!$B:$B, A5) -> 16 | D5: =COUNTIFS(Problems!$B:$B, A5, Problems!$G:$G, "<>UNKNOWN") -> 16 | E5: =COUNTIFS(Problems!$B:$B, A5, Problems!$A:$A, "Solved") -> 0 | F5: =IF(C5>0, E5/C5, 0) -> 0 | G5: =SUMIF(Problems!$B:$B, A5, Problems!$L:$L) -> 820 | H5: =AVERAGEIF(Problems!$B:$B, A5, Problems!$H:$H) -> 1731.25
A6: KINGDOM 5 — THE KINGDOM OF SORTING & GREEDY | B6: 5 | C6: =COUNTIF(Problems!$B:$B, A6) -> 39 | D6: =COUNTIFS(Problems!$B:$B, A6, Problems!$G:$G, "<>UNKNOWN") -> 39 | E6: =COUNTIFS(Problems!$B:$B, A6, Problems!$A:$A, "Solved") -> 0 | F6: =IF(C6>0, E6/C6, 0) -> 0 | G6: =SUMIF(Problems!$B:$B, A6, Problems!$L:$L) -> 1660 | H6: =AVERAGEIF(Problems!$B:$B, A6, Problems!$H:$H) -> 1569.2308
A7: KINGDOM 6 — THE KINGDOM OF STRINGS | B7: 6 | C7: =COUNTIF(Problems!$B:$B, A7) -> 52 | D7: =COUNTIFS(Problems!$B:$B, A7, Problems!$G:$G, "<>UNKNOWN") -> 50 | E7: =COUNTIFS(Problems!$B:$B, A7, Problems!$A:$A, "Solved") -> 0 | F7: =IF(C7>0, E7/C7, 0) -> 0 | G7: =SUMIF(Problems!$B:$B, A7, Problems!$L:$L) -> 1790 | H7: =AVERAGEIF(Problems!$B:$B, A7, Problems!$H:$H) -> 1352
A8: KINGDOM 7 — THE KINGDOM OF BIT MANIPULATION | B8: 4 | C8: =COUNTIF(Problems!$B:$B, A8) -> 30 | D8: =COUNTIFS(Problems!$B:$B, A8, Problems!$G:$G, "<>UNKNOWN") -> 27 | E8: =COUNTIFS(Problems!$B:$B, A8, Problems!$A:$A, "Solved") -> 0 | F8: =IF(C8>0, E8/C8, 0) -> 0 | G8: =SUMIF(Problems!$B:$B, A8, Problems!$L:$L) -> 1165 | H8: =AVERAGEIF(Problems!$B:$B, A8, Problems!$H:$H) -> 1474.0741
A9: KINGDOM 8 — THE KINGDOM OF MATHEMATICS & NUMBER THEORY | B9: 6 | C9: =COUNTIF(Problems!$B:$B, A9) -> 69 | D9: =COUNTIFS(Problems!$B:$B, A9, Problems!$G:$G, "<>UNKNOWN") -> 69 | E9: =COUNTIFS(Problems!$B:$B, A9, Problems!$A:$A, "Solved") -> 0 | F9: =IF(C9>0, E9/C9, 0) -> 0 | G9: =SUMIF(Problems!$B:$B, A9, Problems!$L:$L) -> 3120 | H9: =AVERAGEIF(Problems!$B:$B, A9, Problems!$H:$H) -> 1521.7391
A10: KINGDOM 9 — THE KINGDOM OF RECURSION & BACKTRACKING | B10: 4 | C10: =COUNTIF(Problems!$B:$B, A10) -> 34 | D10: =COUNTIFS(Problems!$B:$B, A10, Problems!$G:$G, "<>UNKNOWN") -> 32 | E10: =COUNTIFS(Problems!$B:$B, A10, Problems!$A:$A, "Solved") -> 0 | F10: =IF(C10>0, E10/C10, 0) -> 0 | G10: =SUMIF(Problems!$B:$B, A10, Problems!$L:$L) -> 1365 | H10: =AVERAGEIF(Problems!$B:$B, A10, Problems!$H:$H) -> 1575
A11: KINGDOM 10 — THE KINGDOM OF STACK & MONOTONIC STACK | B11: 4 | C11: =COUNTIF(Problems!$B:$B, A11) -> 30 | D11: =COUNTIFS(Problems!$B:$B, A11, Problems!$G:$G, "<>UNKNOWN") -> 30 | E11: =COUNTIFS(Problems!$B:$B, A11, Problems!$A:$A, "Solved") -> 0 | F11: =IF(C11>0, E11/C11, 0) -> 0 | G11: =SUMIF(Problems!$B:$B, A11, Problems!$L:$L) -> 1570 | H11: =AVERAGEIF(Problems!$B:$B, A11, Problems!$H:$H) -> 1696.6667
A12: KINGDOM 11 — THE KINGDOM OF QUEUE & DEQUE | B12: 4 | C12: =COUNTIF(Problems!$B:$B, A12) -> 31 | D12: =COUNTIFS(Problems!$B:$B, A12, Problems!$G:$G, "<>UNKNOWN") -> 31 | E12: =COUNTIFS(Problems!$B:$B, A12, Problems!$A:$A, "Solved") -> 0 | F12: =IF(C12>0, E12/C12, 0) -> 0 | G12: =SUMIF(Problems!$B:$B, A12, Problems!$L:$L) -> 1380 | H12: =AVERAGEIF(Problems!$B:$B, A12, Problems!$H:$H) -> 1570.9677
A13: KINGDOM 12 — THE KINGDOM OF LINKED LIST & SIMULATION | B13: 4 | C13: =COUNTIF(Problems!$B:$B, A13) -> 28 | D13: =COUNTIFS(Problems!$B:$B, A13, Problems!$G:$G, "<>UNKNOWN") -> 28 | E13: =COUNTIFS(Problems!$B:$B, A13, Problems!$A:$A, "Solved") -> 0 | F13: =IF(C13>0, E13/C13, 0) -> 0 | G13: =SUMIF(Problems!$B:$B, A13, Problems!$L:$L) -> 1065 | H13: =AVERAGEIF(Problems!$B:$B, A13, Problems!$H:$H) -> 1457.1429
... A22: KINGDOM 25 — THE KINGDOM OF GEOMETRY, INTERACTIVE & MISCELLANEOUS | B22: 5 | C22: =COUNTIF(Problems!$B:$B, A22) -> 25 | D22: =COUNTIFS(Problems!$B:$B, A22, Problems!$G:$G, "<>UNKNOWN") -> 24 | E22: =COUNTIFS(Problems!$B:$B, A22, Problems!$A:$A, "Solved") -> 0 | F22: =IF(C22>0, E22/C22, 0) -> 0 | G22: =SUMIF(Problems!$B:$B, A22, Problems!$L:$L) -> 1720 | H22: =AVERAGEIF(Problems!$B:$B, A22, Problems!$H:$H) -> 1891.6667

Sheet Pattern Summary
A1: Kingdom | B1: Pattern | C1: Total Problems | D1: Verified | E1: Solved | F1: Completion % | G1: Average Rating
A2: KINGDOM 1 — THE KINGDOM OF ARRAYS | B2: Pattern 1.1 — Basic Array Traversal | C2: =COUNTIF(Problems!$C:$C, B2) -> 39 | D2: =COUNTIFS(Problems!$C:$C, B2, Problems!$G:$G, "<>UNKNOWN") -> 39 | E2: =COUNTIFS(Problems!$C:$C, B2, Problems!$A:$A, "Solved") -> 0 | F2: =IF(C2>0, E2/C2, 0) -> 0 | G2: =AVERAGEIF(Problems!$C:$C, B2, Problems!$H:$H) -> 810.25641
A3: KINGDOM 1 — THE KINGDOM OF ARRAYS | B3: Pattern 1.2 — Frequency Counting | C3: =COUNTIF(Problems!$C:$C, B3) -> 26 | D3: =COUNTIFS(Problems!$C:$C, B3, Problems!$G:$G, "<>UNKNOWN") -> 26 | E3: =COUNTIFS(Problems!$C:$C, B3, Problems!$A:$A, "Solved") -> 0 | F3: =IF(C3>0, E3/C3, 0) -> 0 | G3: =AVERAGEIF(Problems!$C:$C, B3, Problems!$H:$H) -> 915.38462
A4: KINGDOM 1 — THE KINGDOM OF ARRAYS | B4: Pattern 1.3 — Simulation on Arrays | C4: =COUNTIF(Problems!$C:$C, B4) -> 31 | D4: =COUNTIFS(Problems!$C:$C, B4, Problems!$G:$G, "<>UNKNOWN") -> 31 | E4: =COUNTIFS(Problems!$C:$C, B4, Problems!$A:$A, "Solved") -> 0 | F4: =IF(C4>0, E4/C4, 0) -> 0 | G4: =AVERAGEIF(Problems!$C:$C, B4, Problems!$H:$H) -> 996.77419
A5: KINGDOM 1 — THE KINGDOM OF ARRAYS | B5: Pattern 1.4 — Sorting Based Arrays | C5: =COUNTIF(Problems!$C:$C, B5) -> 24 | D5: =COUNTIFS(Problems!$C:$C, B5, Problems!$G:$G, "<>UNKNOWN") -> 24 | E5: =COUNTIFS(Problems!$C:$C, B5, Problems!$A:$A, "Solved") -> 0 | F5: =IF(C5>0, E5/C5, 0) -> 0 | G5: =AVERAGEIF(Problems!$C:$C, B5, Problems!$H:$H) -> 1266.6667
A6: KINGDOM 1 — THE KINGDOM OF ARRAYS | B6: Pattern 1.5 — Coordinate Compression | C6: =COUNTIF(Problems!$C:$C, B6) -> 15 | D6: =COUNTIFS(Problems!$C:$C, B6, Problems!$G:$G, "<>UNKNOWN") -> 14 | E6: =COUNTIFS(Problems!$C:$C, B6, Problems!$A:$A, "Solved") -> 0 | F6: =IF(C6>0, E6/C6, 0) -> 0 | G6: =AVERAGEIF(Problems!$C:$C, B6, Problems!$H:$H) -> 1500
A7: KINGDOM 1 — THE KINGDOM OF ARRAYS | B7: Pattern 1.6 — Constructive Arrays | C7: =COUNTIF(Problems!$C:$C, B7) -> 11 | D7: =COUNTIFS(Problems!$C:$C, B7, Problems!$G:$G, "<>UNKNOWN") -> 11 | E7: =COUNTIFS(Problems!$C:$C, B7, Problems!$A:$A, "Solved") -> 0 | F7: =IF(C7>0, E7/C7, 0) -> 0 | G7: =AVERAGEIF(Problems!$C:$C, B7, Problems!$H:$H) -> 1800
A8: KINGDOM 2 — THE KINGDOM OF PREFIX SUM & DIFFERENCE ARRAY | B8: Pattern 2.1 — 1D Prefix Sum | C8: =COUNTIF(Problems!$C:$C, B8) -> 10 | D8: =COUNTIFS(Problems!$C:$C, B8, Problems!$G:$G, "<>UNKNOWN") -> 9 | E8: =COUNTIFS(Problems!$C:$C, B8, Problems!$A:$A, "Solved") -> 0 | F8: =IF(C8>0, E8/C8, 0) -> 0 | G8: =AVERAGEIF(Problems!$C:$C, B8, Problems!$H:$H) -> 1366.6667
A9: KINGDOM 2 — THE KINGDOM OF PREFIX SUM & DIFFERENCE ARRAY | B9: Pattern 2.2 — Prefix Frequency | C9: =COUNTIF(Problems!$C:$C, B9) -> 8 | D9: =COUNTIFS(Problems!$C:$C, B9, Problems!$G:$G, "<>UNKNOWN") -> 8 | E9: =COUNTIFS(Problems!$C:$C, B9, Problems!$A:$A, "Solved") -> 0 | F9: =IF(C9>0, E9/C9, 0) -> 0 | G9: =AVERAGEIF(Problems!$C:$C, B9, Problems!$H:$H) -> 1662.5
A10: KINGDOM 2 — THE KINGDOM OF PREFIX SUM & DIFFERENCE ARRAY | B10: Pattern 2.3 — Difference Array | C10: =COUNTIF(Problems!$C:$C, B10) -> 11 | D10: =COUNTIFS(Problems!$C:$C, B10, Problems!$G:$G, "<>UNKNOWN") -> 11 | E10: =COUNTIFS(Problems!$C:$C, B10, Problems!$A:$A, "Solved") -> 0 | F10: =IF(C10>0, E10/C10, 0) -> 0 | G10: =AVERAGEIF(Problems!$C:$C, B10, Problems!$H:$H) -> 1854.5455
A11: KINGDOM 2 — THE KINGDOM OF PREFIX SUM & DIFFERENCE ARRAY | B11: Pattern 2.4 — Prefix XOR | C11: =COUNTIF(Problems!$C:$C, B11) -> 7 | D11: =COUNTIFS(Problems!$C:$C, B11, Problems!$G:$G, "<>UNKNOWN") -> 7 | E11: =COUNTIFS(Problems!$C:$C, B11, Problems!$A:$A, "Solved") -> 0 | F11: =IF(C11>0, E11/C11, 0) -> 0 | G11: =AVERAGEIF(Problems!$C:$C, B11, Problems!$H:$H) -> 2028.5714
A12: KINGDOM 3 — THE KINGDOM OF TWO POINTERS & SLIDING WINDOW | B12: Pattern 3.1 — Classic Two Pointers | C12: =COUNTIF(Problems!$C:$C, B12) -> 12 | D12: =COUNTIFS(Problems!$C:$C, B12, Problems!$G:$G, "<>UNKNOWN") -> 12 | E12: =COUNTIFS(Problems!$C:$C, B12, Problems!$A:$A, "Solved") -> 0 | F12: =IF(C12>0, E12/C12, 0) -> 0 | G12: =AVERAGEIF(Problems!$C:$C, B12, Problems!$H:$H) -> 1491.6667
A13: KINGDOM 3 — THE KINGDOM OF TWO POINTERS & SLIDING WINDOW | B13: Pattern 3.2 — Opposite Direction Pointers | C13: =COUNTIF(Problems!$C:$C, B13) -> 7 | D13: =COUNTIFS(Problems!$C:$C, B13, Problems!$G:$G, "<>UNKNOWN") -> 7 | E13: =COUNTIFS(Problems!$C:$C, B13, Problems!$A:$A, "Solved") -> 0 | F13: =IF(C13>0, E13/C13, 0) -> 0 | G13: =AVERAGEIF(Problems!$C:$C, B13, Problems!$H:$H) -> 1442.8571
... A107: KINGDOM 25 — THE KINGDOM OF GEOMETRY, INTERACTIVE & MISCELLANEOUS | B107: Pattern 25.5 — Mixed Expert Problems | C107: =COUNTIF(Problems!$C:$C, B107) -> 9 | D107: =COUNTIFS(Problems!$C:$C, B107, Problems!$G:$G, "<>UNKNOWN") -> 9 | E107: =COUNTIFS(Problems!$C:$C, B107, Problems!$A:$A, "Solved") -> 0 | F107: =IF(C107>0, E107/C107, 0) -> 0 | G107: =AVERAGEIF(Problems!$C:$C, B107, Problems!$H:$H) -> 2222.2222

Sheet Statistics
A1: Codeforces Master Dataset - Platform Analytics
A3: Metric | B3: Formula / Value | C3: Description
A4: Total Problems | B4: =COUNTA(Problems!D2:D10000) -> 792 | C4: Total unique Codeforces problems in curriculum
A5: Verified Problems | B5: =COUNTIF(Problems!G2:G10000, "<>UNKNOWN") -> 9982 | C5: Problems verified with official Codeforces API
A6: Solved Problems | B6: =COUNTIF(Problems!A2:A10000, "Solved") -> 0 | C6: Number of problems marked as Solved
A7: Remaining Problems | B7: =B4-B6 -> 792 | C7: Unsolved problems remaining in learning roadmap
A8: Total XP Available | B8: =SUM(Problems!L2:L10000) -> 37390 | C8: Total XP points across all verified problems
A9: Average Problem Rating | B9: =AVERAGE(Problems!H2:H10000) -> 1587.3548 | C9: Mean Codeforces rating across verified problems
A10: Highest Rating | B10: =MAX(Problems!H2:H10000) -> 3300 | C10: Maximum difficulty rating in dataset
A11: Lowest Rating | B11: =MIN(Problems!H2:H10000) -> 800 | C11: Minimum difficulty rating in dataset
A12: Average Estimated Time (mins) | B12: =AVERAGE(Problems!K2:K10000) -> 53.800505 | C12: Average expected solving duration per problem
A13: Kingdom Completion Rate | B13: =AVERAGE('Kingdom Summary'!F2:F100) -> 0 | C13: Average completion % across all kingdoms
A14: Pattern Completion Rate | B14: =AVERAGE('Pattern Summary'!F2:F500) -> 0 | C14: Average completion % across all patterns

Sheet Metadata
A1: System Metadata & Mapping Standards
A3: Generation Date: | B3: 2026-07-29 21:52:34
A4: Last Updated: | B4: 2026-07-29 21:52:34
A6: Rating Range | B6: Difficulty Tier | C6: Estimated Time (mins) | D6: XP Points
A7: 800-1000 | B7: Easy | C7: 15 | D7: 10
A8: 1100-1300 | B8: Easy+ | C8: 25 | D8: 20
A9: 1400-1600 | B9: Medium | C9: 40 | D9: 35
A10: 1700-1900 | B10: Hard | C10: 60 | D10: 55
A11: 2000-2200 | B11: Hard+ | C11: 90 | D11: 80
A12: 2300-2500 | B12: Expert | C12: 120 | D12: 110
A13: 2600-3000 | B13: Master | C13: 180 | D13: 150
A14: 3100+ | B14: Master | C14: 240 | D14: 220
A17: Kingdom # | B17: Kingdom Name | C17: Total Patterns
A18: 1 | B18: KINGDOM 1 — THE KINGDOM OF ARRAYS | C18: 6
A19: 2 | B19: KINGDOM 2 — THE KINGDOM OF PREFIX SUM & DIFFERENCE ARRAY | C19: 4
A20: 3 | B20: KINGDOM 3 — THE KINGDOM OF TWO POINTERS & SLIDING WINDOW | C20: 4
A21: 4 | B21: KINGDOM 4 — THE KINGDOM OF BINARY SEARCH | C21: 4
A22: 5 | B22: KINGDOM 5 — THE KINGDOM OF SORTING & GREEDY | C22: 5
A23: 6 | B23: KINGDOM 6 — THE KINGDOM OF STRINGS | C23: 6
A24: 7 | B24: KINGDOM 7 — THE KINGDOM OF BIT MANIPULATION | C24: 4
A25: 8 | B25: KINGDOM 8 — THE KINGDOM OF MATHEMATICS & NUMBER THEORY | C25: 6
A26: 9 | B26: KINGDOM 9 — THE KINGDOM OF RECURSION & BACKTRACKING | C26: 4
A27: 10 | B27: KINGDOM 10 — THE KINGDOM OF STACK & MONOTONIC STACK | C27: 4
A28: 11 | B28: KINGDOM 11 — THE KINGDOM OF QUEUE & DEQUE | C28: 4
A29: 12 | B29: KINGDOM 12 — THE KINGDOM OF LINKED LIST & SIMULATION | C29: 4
... A38: 21 | B38: KINGDOM 25 — THE KINGDOM OF GEOMETRY, INTERACTIVE & MISCELLANEOUS | C38: 5
A41: Kingdom | B41: Pattern Name
A42: KINGDOM 1 — THE KINGDOM OF ARRAYS | B42: Pattern 1.1 — Basic Array Traversal
A43: KINGDOM 1 — THE KINGDOM OF ARRAYS | B43: Pattern 1.2 — Frequency Counting
A44: KINGDOM 1 — THE KINGDOM OF ARRAYS | B44: Pattern 1.3 — Simulation on Arrays
A45: KINGDOM 1 — THE KINGDOM OF ARRAYS | B45: Pattern 1.4 — Sorting Based Arrays
A46: KINGDOM 1 — THE KINGDOM OF ARRAYS | B46: Pattern 1.5 — Coordinate Compression
A47: KINGDOM 1 — THE KINGDOM OF ARRAYS | B47: Pattern 1.6 — Constructive Arrays
A48: KINGDOM 2 — THE KINGDOM OF PREFIX SUM & DIFFERENCE ARRAY | B48: Pattern 2.1 — 1D Prefix Sum
A49: KINGDOM 2 — THE KINGDOM OF PREFIX SUM & DIFFERENCE ARRAY | B49: Pattern 2.2 — Prefix Frequency
A50: KINGDOM 2 — THE KINGDOM OF PREFIX SUM & DIFFERENCE ARRAY | B50: Pattern 2.3 — Difference Array
A51: KINGDOM 2 — THE KINGDOM OF PREFIX SUM & DIFFERENCE ARRAY | B51: Pattern 2.4 — Prefix XOR
A52: KINGDOM 3 — THE KINGDOM OF TWO POINTERS & SLIDING WINDOW | B52: Pattern 3.1 — Classic Two Pointers
... A147: KINGDOM 25 — THE KINGDOM OF GEOMETRY, INTERACTIVE & MISCELLANEOUS | B147: Pattern 25.5 — Mixed Expert Problems
