Workbook

Sheet Problems
A1: Status | B1: Category | C1: Subtopic | D1: Problem Code | E1: Problem Name | F1: Difficulty | G1: Topics | H1: Estimated Time | I1: XP | J1: Open Link | K1: Notes | L1: Platform
A2: Unsolved | B2: KINGDOM 1 — THE KINGDOM OF ARRAYS | C2: Pattern 1.1 — Basic Array Traversal | D2: FLOW001 | E2: Add Two Numbers | F2: Beginner | G2: basic math, arrays | H2: 15 | I2: 10 | J2: https://www.codechef.com/problems/FLOW001 | L2: codechef
A3: Unsolved | B3: KINGDOM 1 — THE KINGDOM OF ARRAYS | C3: Pattern 1.1 — Basic Array Traversal | D3: FLOW002 | E3: Find Remainder | F3: Beginner | G3: basic math, arrays | H3: 15 | I3: 10 | J3: https://www.codechef.com/problems/FLOW002 | L3: codechef
A4: Unsolved | B4: KINGDOM 1 — THE KINGDOM OF ARRAYS | C4: Pattern 1.1 — Basic Array Traversal | D4: FLOW004 | E4: First and Last Digit | F4: Beginner | G4: arrays, traversal | H4: 15 | I4: 10 | J4: https://www.codechef.com/problems/FLOW004 | L4: codechef
A5: Unsolved | B5: KINGDOM 1 — THE KINGDOM OF ARRAYS | C5: Pattern 1.1 — Basic Array Traversal | D5: FLOW006 | E5: Sum of Digits | F5: Beginner | G5: arrays, math | H5: 15 | I5: 10 | J5: https://www.codechef.com/problems/FLOW006 | L5: codechef
A6: Unsolved | B6: KINGDOM 1 — THE KINGDOM OF ARRAYS | C6: Pattern 1.1 — Basic Array Traversal | D6: FLOW007 | E6: Reverse The Number | F6: Beginner | G6: arrays, implementation | H6: 15 | I6: 10 | J6: https://www.codechef.com/problems/FLOW007 | L6: codechef
A7: Unsolved | B7: KINGDOM 1 — THE KINGDOM OF ARRAYS | C7: Pattern 1.1 — Basic Array Traversal | D7: START01 | E7: Number Mirror | F7: Beginner | G7: basic I/O, arrays | H7: 15 | I7: 10 | J7: https://www.codechef.com/problems/START01 | L7: codechef
A8: Unsolved | B8: KINGDOM 1 — THE KINGDOM OF ARRAYS | C8: Pattern 1.1 — Basic Array Traversal | D8: HS08TEST | E8: ATM | F8: Beginner | G8: basic math, implementation | H8: 15 | I8: 10 | J8: https://www.codechef.com/problems/HS08TEST | L8: codechef
A9: Unsolved | B9: KINGDOM 1 — THE KINGDOM OF ARRAYS | C9: Pattern 1.1 — Basic Array Traversal | D9: LUCKFOUR | E9: Lucky Four | F9: Beginner | G9: traversal, counting | H9: 15 | I9: 10 | J9: https://www.codechef.com/problems/LUCKFOUR | L9: codechef
A10: Unsolved | B10: KINGDOM 1 — THE KINGDOM OF ARRAYS | C10: Pattern 1.2 — Frequency Counting | D10: VCS | E10: Version Control System | F10: Easy | G10: frequency count, arrays | H10: 25 | I10: 20 | J10: https://www.codechef.com/problems/VCS | L10: codechef
A11: Unsolved | B11: KINGDOM 1 — THE KINGDOM OF ARRAYS | C11: Pattern 1.2 — Frequency Counting | D11: RAINBOWA | E11: Rainbow Array | F11: Easy | G11: frequency, validation | H11: 25 | I11: 20 | J11: https://www.codechef.com/problems/RAINBOWA | L11: codechef
A12: Unsolved | B12: KINGDOM 1 — THE KINGDOM OF ARRAYS | C12: Pattern 1.2 — Frequency Counting | D12: TLG | E12: The Lead Game | F12: Easy | G12: cumulative count, arrays | H12: 25 | I12: 20 | J12: https://www.codechef.com/problems/TLG | L12: codechef
A13: Unsolved | B13: KINGDOM 1 — THE KINGDOM OF ARRAYS | C13: Pattern 1.2 — Frequency Counting | D13: NOTINCOM | E13: Nothing in Common | F13: Easy | G13: frequency, set intersection | H13: 25 | I13: 20 | J13: https://www.codechef.com/problems/NOTINCOM | L13: codechef
... A840: Unsolved | B840: KINGDOM 25 — THE KINGDOM OF GEOMETRY, INTERACTIVE & MISCELLANEOUS | C840: Pattern 25.5 — Mixed Expert Problems | D840: EXPERT6 | E840: Fast Fourier Transform FFT Polynomial Multiplication | F840: Expert | G840: Cooley-Tukey FFT complex roots unity | H840: 180 | I840: 180 | J840: https://www.codechef.com/problems/EXPERT6 | L840: codechef

Sheet Kingdom Summary
A1: Kingdom | B1: Patterns | C1: Total Problems | D1: Verified Problems | E1: Solved | F1: Completion % | G1: Total XP | H1: Average Estimated Time (mins)
A2: KINGDOM 1 — THE KINGDOM OF ARRAYS | B2: 6 | C2: =COUNTIF(Problems!$B:$B, A2) | D2: =COUNTIFS(Problems!$B:$B, A2, Problems!$D:$D, "<>UNKNOWN") | E2: =COUNTIFS(Problems!$B:$B, A2, Problems!$A:$A, "Solved") | F2: =IF(C2>0, E2/C2, 0) | G2: =SUMIF(Problems!$B:$B, A2, Problems!$I:$I) | H2: =AVERAGEIF(Problems!$B:$B, A2, Problems!$H:$H)
A3: KINGDOM 2 — THE KINGDOM OF PREFIX SUM & DIFFERENCE ARRAY | B3: 4 | C3: =COUNTIF(Problems!$B:$B, A3) | D3: =COUNTIFS(Problems!$B:$B, A3, Problems!$D:$D, "<>UNKNOWN") | E3: =COUNTIFS(Problems!$B:$B, A3, Problems!$A:$A, "Solved") | F3: =IF(C3>0, E3/C3, 0) | G3: =SUMIF(Problems!$B:$B, A3, Problems!$I:$I) | H3: =AVERAGEIF(Problems!$B:$B, A3, Problems!$H:$H)
A4: KINGDOM 3 — THE KINGDOM OF TWO POINTERS & SLIDING WINDOW | B4: 4 | C4: =COUNTIF(Problems!$B:$B, A4) | D4: =COUNTIFS(Problems!$B:$B, A4, Problems!$D:$D, "<>UNKNOWN") | E4: =COUNTIFS(Problems!$B:$B, A4, Problems!$A:$A, "Solved") | F4: =IF(C4>0, E4/C4, 0) | G4: =SUMIF(Problems!$B:$B, A4, Problems!$I:$I) | H4: =AVERAGEIF(Problems!$B:$B, A4, Problems!$H:$H)
A5: KINGDOM 4 — THE KINGDOM OF BINARY SEARCH | B5: 4 | C5: =COUNTIF(Problems!$B:$B, A5) | D5: =COUNTIFS(Problems!$B:$B, A5, Problems!$D:$D, "<>UNKNOWN") | E5: =COUNTIFS(Problems!$B:$B, A5, Problems!$A:$A, "Solved") | F5: =IF(C5>0, E5/C5, 0) | G5: =SUMIF(Problems!$B:$B, A5, Problems!$I:$I) | H5: =AVERAGEIF(Problems!$B:$B, A5, Problems!$H:$H)
A6: KINGDOM 5 — THE KINGDOM OF SORTING & GREEDY | B6: 5 | C6: =COUNTIF(Problems!$B:$B, A6) | D6: =COUNTIFS(Problems!$B:$B, A6, Problems!$D:$D, "<>UNKNOWN") | E6: =COUNTIFS(Problems!$B:$B, A6, Problems!$A:$A, "Solved") | F6: =IF(C6>0, E6/C6, 0) | G6: =SUMIF(Problems!$B:$B, A6, Problems!$I:$I) | H6: =AVERAGEIF(Problems!$B:$B, A6, Problems!$H:$H)
A7: KINGDOM 6 — THE KINGDOM OF STRINGS | B7: 6 | C7: =COUNTIF(Problems!$B:$B, A7) | D7: =COUNTIFS(Problems!$B:$B, A7, Problems!$D:$D, "<>UNKNOWN") | E7: =COUNTIFS(Problems!$B:$B, A7, Problems!$A:$A, "Solved") | F7: =IF(C7>0, E7/C7, 0) | G7: =SUMIF(Problems!$B:$B, A7, Problems!$I:$I) | H7: =AVERAGEIF(Problems!$B:$B, A7, Problems!$H:$H)
A8: KINGDOM 7 — THE KINGDOM OF BIT MANIPULATION | B8: 4 | C8: =COUNTIF(Problems!$B:$B, A8) | D8: =COUNTIFS(Problems!$B:$B, A8, Problems!$D:$D, "<>UNKNOWN") | E8: =COUNTIFS(Problems!$B:$B, A8, Problems!$A:$A, "Solved") | F8: =IF(C8>0, E8/C8, 0) | G8: =SUMIF(Problems!$B:$B, A8, Problems!$I:$I) | H8: =AVERAGEIF(Problems!$B:$B, A8, Problems!$H:$H)
A9: KINGDOM 8 — THE KINGDOM OF MATHEMATICS & NUMBER THEORY | B9: 6 | C9: =COUNTIF(Problems!$B:$B, A9) | D9: =COUNTIFS(Problems!$B:$B, A9, Problems!$D:$D, "<>UNKNOWN") | E9: =COUNTIFS(Problems!$B:$B, A9, Problems!$A:$A, "Solved") | F9: =IF(C9>0, E9/C9, 0) | G9: =SUMIF(Problems!$B:$B, A9, Problems!$I:$I) | H9: =AVERAGEIF(Problems!$B:$B, A9, Problems!$H:$H)
A10: KINGDOM 9 — THE KINGDOM OF RECURSION & BACKTRACKING | B10: 4 | C10: =COUNTIF(Problems!$B:$B, A10) | D10: =COUNTIFS(Problems!$B:$B, A10, Problems!$D:$D, "<>UNKNOWN") | E10: =COUNTIFS(Problems!$B:$B, A10, Problems!$A:$A, "Solved") | F10: =IF(C10>0, E10/C10, 0) | G10: =SUMIF(Problems!$B:$B, A10, Problems!$I:$I) | H10: =AVERAGEIF(Problems!$B:$B, A10, Problems!$H:$H)
A11: KINGDOM 10 — THE KINGDOM OF STACK & MONOTONIC STACK | B11: 4 | C11: =COUNTIF(Problems!$B:$B, A11) | D11: =COUNTIFS(Problems!$B:$B, A11, Problems!$D:$D, "<>UNKNOWN") | E11: =COUNTIFS(Problems!$B:$B, A11, Problems!$A:$A, "Solved") | F11: =IF(C11>0, E11/C11, 0) | G11: =SUMIF(Problems!$B:$B, A11, Problems!$I:$I) | H11: =AVERAGEIF(Problems!$B:$B, A11, Problems!$H:$H)
A12: KINGDOM 11 — THE KINGDOM OF QUEUE & DEQUE | B12: 4 | C12: =COUNTIF(Problems!$B:$B, A12) | D12: =COUNTIFS(Problems!$B:$B, A12, Problems!$D:$D, "<>UNKNOWN") | E12: =COUNTIFS(Problems!$B:$B, A12, Problems!$A:$A, "Solved") | F12: =IF(C12>0, E12/C12, 0) | G12: =SUMIF(Problems!$B:$B, A12, Problems!$I:$I) | H12: =AVERAGEIF(Problems!$B:$B, A12, Problems!$H:$H)
A13: KINGDOM 12 — THE KINGDOM OF LINKED LIST & SIMULATION | B13: 4 | C13: =COUNTIF(Problems!$B:$B, A13) | D13: =COUNTIFS(Problems!$B:$B, A13, Problems!$D:$D, "<>UNKNOWN") | E13: =COUNTIFS(Problems!$B:$B, A13, Problems!$A:$A, "Solved") | F13: =IF(C13>0, E13/C13, 0) | G13: =SUMIF(Problems!$B:$B, A13, Problems!$I:$I) | H13: =AVERAGEIF(Problems!$B:$B, A13, Problems!$H:$H)
... A26: KINGDOM 25 — THE KINGDOM OF GEOMETRY, INTERACTIVE & MISCELLANEOUS | B26: 5 | C26: =COUNTIF(Problems!$B:$B, A26) | D26: =COUNTIFS(Problems!$B:$B, A26, Problems!$D:$D, "<>UNKNOWN") | E26: =COUNTIFS(Problems!$B:$B, A26, Problems!$A:$A, "Solved") | F26: =IF(C26>0, E26/C26, 0) | G26: =SUMIF(Problems!$B:$B, A26, Problems!$I:$I) | H26: =AVERAGEIF(Problems!$B:$B, A26, Problems!$H:$H)

Sheet Pattern Summary
A1: Kingdom | B1: Pattern | C1: Total Problems | D1: Verified | E1: Solved | F1: Completion % | G1: Average Estimated Time (mins)
A2: KINGDOM 1 — THE KINGDOM OF ARRAYS | B2: Pattern 1.1 — Basic Array Traversal | C2: =COUNTIF(Problems!$C:$C, B2) | D2: =COUNTIFS(Problems!$C:$C, B2, Problems!$D:$D, "<>UNKNOWN") | E2: =COUNTIFS(Problems!$C:$C, B2, Problems!$A:$A, "Solved") | F2: =IF(C2>0, E2/C2, 0) | G2: =AVERAGEIF(Problems!$C:$C, B2, Problems!$H:$H)
A3: KINGDOM 1 — THE KINGDOM OF ARRAYS | B3: Pattern 1.2 — Frequency Counting | C3: =COUNTIF(Problems!$C:$C, B3) | D3: =COUNTIFS(Problems!$C:$C, B3, Problems!$D:$D, "<>UNKNOWN") | E3: =COUNTIFS(Problems!$C:$C, B3, Problems!$A:$A, "Solved") | F3: =IF(C3>0, E3/C3, 0) | G3: =AVERAGEIF(Problems!$C:$C, B3, Problems!$H:$H)
A4: KINGDOM 1 — THE KINGDOM OF ARRAYS | B4: Pattern 1.3 — Simulation on Arrays | C4: =COUNTIF(Problems!$C:$C, B4) | D4: =COUNTIFS(Problems!$C:$C, B4, Problems!$D:$D, "<>UNKNOWN") | E4: =COUNTIFS(Problems!$C:$C, B4, Problems!$A:$A, "Solved") | F4: =IF(C4>0, E4/C4, 0) | G4: =AVERAGEIF(Problems!$C:$C, B4, Problems!$H:$H)
A5: KINGDOM 1 — THE KINGDOM OF ARRAYS | B5: Pattern 1.4 — Sorting Based Arrays | C5: =COUNTIF(Problems!$C:$C, B5) | D5: =COUNTIFS(Problems!$C:$C, B5, Problems!$D:$D, "<>UNKNOWN") | E5: =COUNTIFS(Problems!$C:$C, B5, Problems!$A:$A, "Solved") | F5: =IF(C5>0, E5/C5, 0) | G5: =AVERAGEIF(Problems!$C:$C, B5, Problems!$H:$H)
A6: KINGDOM 1 — THE KINGDOM OF ARRAYS | B6: Pattern 1.5 — Coordinate Compression | C6: =COUNTIF(Problems!$C:$C, B6) | D6: =COUNTIFS(Problems!$C:$C, B6, Problems!$D:$D, "<>UNKNOWN") | E6: =COUNTIFS(Problems!$C:$C, B6, Problems!$A:$A, "Solved") | F6: =IF(C6>0, E6/C6, 0) | G6: =AVERAGEIF(Problems!$C:$C, B6, Problems!$H:$H)
A7: KINGDOM 1 — THE KINGDOM OF ARRAYS | B7: Pattern 1.6 — Constructive Arrays | C7: =COUNTIF(Problems!$C:$C, B7) | D7: =COUNTIFS(Problems!$C:$C, B7, Problems!$D:$D, "<>UNKNOWN") | E7: =COUNTIFS(Problems!$C:$C, B7, Problems!$A:$A, "Solved") | F7: =IF(C7>0, E7/C7, 0) | G7: =AVERAGEIF(Problems!$C:$C, B7, Problems!$H:$H)
A8: KINGDOM 2 — THE KINGDOM OF PREFIX SUM & DIFFERENCE ARRAY | B8: Pattern 2.1 — 1D Prefix Sum | C8: =COUNTIF(Problems!$C:$C, B8) | D8: =COUNTIFS(Problems!$C:$C, B8, Problems!$D:$D, "<>UNKNOWN") | E8: =COUNTIFS(Problems!$C:$C, B8, Problems!$A:$A, "Solved") | F8: =IF(C8>0, E8/C8, 0) | G8: =AVERAGEIF(Problems!$C:$C, B8, Problems!$H:$H)
A9: KINGDOM 2 — THE KINGDOM OF PREFIX SUM & DIFFERENCE ARRAY | B9: Pattern 2.2 — Prefix Frequency | C9: =COUNTIF(Problems!$C:$C, B9) | D9: =COUNTIFS(Problems!$C:$C, B9, Problems!$D:$D, "<>UNKNOWN") | E9: =COUNTIFS(Problems!$C:$C, B9, Problems!$A:$A, "Solved") | F9: =IF(C9>0, E9/C9, 0) | G9: =AVERAGEIF(Problems!$C:$C, B9, Problems!$H:$H)
A10: KINGDOM 2 — THE KINGDOM OF PREFIX SUM & DIFFERENCE ARRAY | B10: Pattern 2.3 — Difference Array | C10: =COUNTIF(Problems!$C:$C, B10) | D10: =COUNTIFS(Problems!$C:$C, B10, Problems!$D:$D, "<>UNKNOWN") | E10: =COUNTIFS(Problems!$C:$C, B10, Problems!$A:$A, "Solved") | F10: =IF(C10>0, E10/C10, 0) | G10: =AVERAGEIF(Problems!$C:$C, B10, Problems!$H:$H)
A11: KINGDOM 2 — THE KINGDOM OF PREFIX SUM & DIFFERENCE ARRAY | B11: Pattern 2.4 — Prefix XOR | C11: =COUNTIF(Problems!$C:$C, B11) | D11: =COUNTIFS(Problems!$C:$C, B11, Problems!$D:$D, "<>UNKNOWN") | E11: =COUNTIFS(Problems!$C:$C, B11, Problems!$A:$A, "Solved") | F11: =IF(C11>0, E11/C11, 0) | G11: =AVERAGEIF(Problems!$C:$C, B11, Problems!$H:$H)
A12: KINGDOM 3 — THE KINGDOM OF TWO POINTERS & SLIDING WINDOW | B12: Pattern 3.1 — Classic Two Pointers | C12: =COUNTIF(Problems!$C:$C, B12) | D12: =COUNTIFS(Problems!$C:$C, B12, Problems!$D:$D, "<>UNKNOWN") | E12: =COUNTIFS(Problems!$C:$C, B12, Problems!$A:$A, "Solved") | F12: =IF(C12>0, E12/C12, 0) | G12: =AVERAGEIF(Problems!$C:$C, B12, Problems!$H:$H)
A13: KINGDOM 3 — THE KINGDOM OF TWO POINTERS & SLIDING WINDOW | B13: Pattern 3.2 — Opposite Direction Pointers | C13: =COUNTIF(Problems!$C:$C, B13) | D13: =COUNTIFS(Problems!$C:$C, B13, Problems!$D:$D, "<>UNKNOWN") | E13: =COUNTIFS(Problems!$C:$C, B13, Problems!$A:$A, "Solved") | F13: =IF(C13>0, E13/C13, 0) | G13: =AVERAGEIF(Problems!$C:$C, B13, Problems!$H:$H)
... A115: KINGDOM 25 — THE KINGDOM OF GEOMETRY, INTERACTIVE & MISCELLANEOUS | B115: Pattern 25.5 — Mixed Expert Problems | C115: =COUNTIF(Problems!$C:$C, B115) | D115: =COUNTIFS(Problems!$C:$C, B115, Problems!$D:$D, "<>UNKNOWN") | E115: =COUNTIFS(Problems!$C:$C, B115, Problems!$A:$A, "Solved") | F115: =IF(C115>0, E115/C115, 0) | G115: =AVERAGEIF(Problems!$C:$C, B115, Problems!$H:$H)

Sheet Statistics
A1: CodeChef Master Dataset - Platform Analytics
A3: Metric | B3: Formula / Value | C3: Description
A4: Total Problems | B4: =COUNTA(Problems!D2:D10000) | C4: Total unique CodeChef problems in curriculum
A5: Verified Problems | B5: =COUNTIF(Problems!D2:D10000, "<>UNKNOWN") | C5: Problems verified with official CodeChef Practice codes
A6: Solved Problems | B6: =COUNTIF(Problems!A2:A10000, "Solved") | C6: Number of problems marked as Solved
A7: Remaining Problems | B7: =B4-B6 | C7: Unsolved problems remaining in learning roadmap
A8: Total XP Available | B8: =SUM(Problems!I2:I10000) | C8: Total XP points across all verified problems
A9: Average Estimated Time (mins) | B9: =AVERAGE(Problems!H2:H10000) | C9: Average expected solving duration per problem
A10: Max Estimated Time (mins) | B10: =MAX(Problems!H2:H10000) | C10: Maximum expected duration tier
A11: Min Estimated Time (mins) | B11: =MIN(Problems!H2:H10000) | C11: Minimum expected duration tier
A12: Kingdom Completion Rate | B12: =AVERAGE('Kingdom Summary'!F2:F100) | C12: Average completion % across all kingdoms
A13: Pattern Completion Rate | B13: =AVERAGE('Pattern Summary'!F2:F500) | C13: Average completion % across all patterns

Sheet Metadata
A1: CodeChef Dataset Metadata & Difficulty Tiers
A3: Generation Date: | B3: 2026-07-29 22:45:43
A4: Platform: | B4: codechef
A6: Difficulty Tier | B6: Estimated Time (mins) | C6: XP Points
A7: Beginner | B7: 15 | C7: 10
A8: Easy | B8: 25 | C8: 20
A9: Easy-Medium | B9: 40 | C9: 35
A10: Medium | B10: 60 | C10: 55
A11: Medium-Hard | B11: 90 | C11: 80
A12: Hard | B12: 120 | C12: 120
A13: Expert | B13: 180 | C13: 180
A16: Kingdom # | B16: Kingdom Name | C16: Total Patterns
A17: 1 | B17: KINGDOM 1 — THE KINGDOM OF ARRAYS | C17: 6
A18: 2 | B18: KINGDOM 2 — THE KINGDOM OF PREFIX SUM & DIFFERENCE ARRAY | C18: 4
A19: 3 | B19: KINGDOM 3 — THE KINGDOM OF TWO POINTERS & SLIDING WINDOW | C19: 4
A20: 4 | B20: KINGDOM 4 — THE KINGDOM OF BINARY SEARCH | C20: 4
A21: 5 | B21: KINGDOM 5 — THE KINGDOM OF SORTING & GREEDY | C21: 5
A22: 6 | B22: KINGDOM 6 — THE KINGDOM OF STRINGS | C22: 6
A23: 7 | B23: KINGDOM 7 — THE KINGDOM OF BIT MANIPULATION | C23: 4
A24: 8 | B24: KINGDOM 8 — THE KINGDOM OF MATHEMATICS & NUMBER THEORY | C24: 6
A25: 9 | B25: KINGDOM 9 — THE KINGDOM OF RECURSION & BACKTRACKING | C25: 4
A26: 10 | B26: KINGDOM 10 — THE KINGDOM OF STACK & MONOTONIC STACK | C26: 4
A27: 11 | B27: KINGDOM 11 — THE KINGDOM OF QUEUE & DEQUE | C27: 4
A28: 12 | B28: KINGDOM 12 — THE KINGDOM OF LINKED LIST & SIMULATION | C28: 4
... A41: 25 | B41: KINGDOM 25 — THE KINGDOM OF GEOMETRY, INTERACTIVE & MISCELLANEOUS | C41: 5
